{
    "perf": [
        {
            "stat": [
                "main",
                "entry",
                0.014815971138887107,
                0.028114,
                0.011044,
                178240,
                178240,
                0.0,
                0.0,
                1614155525.0738261,
                592629517864131
            ],
            "sub": [
                {
                    "stat": [
                        "doParsingAndDesignResolution",
                        "entry",
                        6.6684389711590484,
                        0.031047000000000002,
                        0.019269999999999999,
                        178688,
                        179488,
                        0.0,
                        0.0,
                        1614155531.7274489,
                        592651425023361
                    ],
                    "sub": []
                },
                {
                    "stat": [
                        "doParsingAndDesignResolution",
                        "exit",
                        6.6855929711600766,
                        0.047405000000000003,
                        0.020015000000000002,
                        180088,
                        181060,
                        0.0,
                        0.0,
                        1614155531.7446029,
                        592651481517105
                    ],
                    "sub": []
                },
                {
                    "stat": [
                        "doPostDesignResolutionToVir2Vcs",
                        "entry",
                        6.685862971120514,
                        0.047594999999999998,
                        0.020094999999999998,
                        180088,
                        181060,
                        0.0,
                        0.0,
                        1614155531.744873,
                        592651482371385
                    ],
                    "sub": [
                        {
                            "stat": [
                                "doUptoVir2VcsNoSepCleanup",
                                "entry",
                                6.6961409711511806,
                                0.056979000000000002,
                                0.020989000000000001,
                                180944,
                                181060,
                                0.0,
                                0.0,
                                1614155531.755151,
                                592651516234416
                            ],
                            "sub": []
                        },
                        {
                            "stat": [
                                "doUptoVir2VcsNoSepCleanup",
                                "exit",
                                6.8194039711961523,
                                0.155719,
                                0.028312,
                                184076,
                                196432,
                                0.0030820000000000001,
                                0.013716000000000001,
                                1614155531.8784139,
                                592651922103456
                            ],
                            "sub": []
                        },
                        {
                            "stat": [
                                "doRadify_vir2vcsAll",
                                "entry",
                                6.8194809712003917,
                                0.15578600000000001,
                                0.028323999999999998,
                                184076,
                                196432,
                                0.0030820000000000001,
                                0.013716000000000001,
                                1614155531.8784909,
                                592651922291460
                            ],
                            "sub": []
                        },
                        {
                            "stat": [
                                "doRadify_vir2vcsAll",
                                "exit",
                                6.825498971156776,
                                0.161803,
                                0.028323999999999998,
                                184076,
                                196432,
                                0.0030820000000000001,
                                0.013716000000000001,
                                1614155531.8845091,
                                592651942156569
                            ],
                            "sub": []
                        }
                    ]
                },
                {
                    "stat": [
                        "doPostDesignResolutionToVir2Vcs",
                        "exit",
                        6.8255479711806402,
                        0.161853,
                        0.028323999999999998,
                        184076,
                        196432,
                        0.0030820000000000001,
                        0.013716000000000001,
                        1614155531.884558,
                        592651942261980
                    ],
                    "sub": []
                },
                {
                    "stat": [
                        "doGAToPass2",
                        "entry",
                        6.8255779711762443,
                        0.161879,
                        0.028327999999999999,
                        184076,
                        196432,
                        0.0030820000000000001,
                        0.013716000000000001,
                        1614155531.884588,
                        592651942348332
                    ],
                    "sub": [
                        {
                            "stat": [
                                "DoPass2",
                                "entry",
                                6.8271259712055326,
                                0.16342699999999999,
                                0.028327999999999999,
                                182596,
                                196432,
                                0.0030820000000000001,
                                0.013716000000000001,
                                1614155531.8861361,
                                592651947487098
                            ],
                            "sub": []
                        },
                        {
                            "stat": [
                                "DoPass2",
                                "exit",
                                6.9205379711929709,
                                0.247139,
                                0.035305000000000003,
                                188956,
                                196432,
                                0.0030820000000000001,
                                0.016403999999999998,
                                1614155531.979548,
                                592652255038596
                            ],
                            "sub": []
                        }
                    ]
                },
                {
                    "stat": [
                        "doGAToPass2",
                        "exit",
                        6.9236269711982459,
                        0.24921199999999999,
                        0.036322,
                        188956,
                        196432,
                        0.0030820000000000001,
                        0.016403999999999998,
                        1614155531.9826369,
                        592652265217212
                    ],
                    "sub": []
                }
            ]
        },
        {
            "stat": [
                "main",
                "exit",
                6.923921971116215,
                0.249469,
                0.036359000000000002,
                188948,
                196432,
                0.0030820000000000001,
                0.016403999999999998,
                1614155531.9829321,
                592652266178814
            ],
            "sub": []
        }
    ],
    "CompileProcesses": [
        "cgproc.6051.json"
    ],
    "PrevCompiledModules": {
        "flash": {
            "TKY6z_d": {
                "checksum": 0,
                "bytes": 89394,
                "mod": "flash",
                "mode": 4,
                "archive": "archive.52/_prev_archive_1.a",
                "out": "TKY6z_d.o"
            }
        },
        "BUFFER": {
            "sIeQK_d": {
                "checksum": 0,
                "bytes": 3750,
                "mod": "BUFFER",
                "mode": 4,
                "archive": "archive.52/_prev_archive_1.a",
                "out": "sIeQK_d.o"
            }
        },
        "...MASTER...": {
            "amcQw_d": {
                "checksum": 0,
                "bytes": 4696,
                "mod": "...MASTER...",
                "mode": 4,
                "out": "objs/amcQw_d.o"
            }
        },
        "test": {
            "x9Hvb_d": {
                "checksum": 0,
                "bytes": 80276,
                "mod": "test",
                "out": "x9Hvb_d.o",
                "mode": 4,
                "archive": "archive.52/_6051_archive_1.a"
            }
        }
    },
    "cycles_program_begin": 592629517546983,
    "LVLData": [
        "SIM"
    ],
    "MlibObjs": {},
    "NameTable": {
        "flash": [
            "flash",
            "TKY6z",
            "module",
            1
        ],
        "BUFFER": [
            "BUFFER",
            "sIeQK",
            "module",
            4
        ],
        "test": [
            "test",
            "x9Hvb",
            "module",
            2
        ],
        "...MASTER...": [
            "SIM",
            "amcQw",
            "module",
            3
        ]
    },
    "CompileStrategy": "fullobj",
    "CompileStatus": "Successful",
    "cpu_cycles_pass2_start": 592651947493029,
    "PEModules": [],
    "CurCompileModules": [
        "...MASTER...",
        "flash",
        "BUFFER",
        "test",
        "test"
    ],
    "stat": {
        "CodeGen(%)": 34.047380529081259,
        "nQuads": 8520,
        "nMops": 22597,
        "Frontend(%)": 65.952619470918748,
        "ru_self_cgstart": {
            "ru_majflt": 0,
            "ru_utime_sec": 0.16348199999999999,
            "ru_minflt": 23981,
            "ru_maxrss_kb": 58996,
            "ru_stime_sec": 0.028327999999999999,
            "ru_nivcsw": 65,
            "ru_nvcsw": 51
        },
        "ru_childs_cgstart": {
            "ru_majflt": 0,
            "ru_utime_sec": 0.0030820000000000001,
            "ru_minflt": 4271,
            "ru_maxrss_kb": 8820,
            "ru_stime_sec": 0.013716000000000001,
            "ru_nivcsw": 18,
            "ru_nvcsw": 8
        },
        "ru_self_end": {
            "ru_majflt": 0,
            "ru_utime_sec": 0.249469,
            "ru_minflt": 27270,
            "ru_maxrss_kb": 68136,
            "ru_stime_sec": 0.036415000000000003,
            "ru_nivcsw": 72,
            "ru_nvcsw": 52
        },
        "cpu_cycles_cgstart": 592651947563916,
        "ru_childs_end": {
            "ru_majflt": 0,
            "ru_utime_sec": 0.0030820000000000001,
            "ru_minflt": 4861,
            "ru_maxrss_kb": 12016,
            "ru_stime_sec": 0.016403999999999998,
            "ru_nivcsw": 20,
            "ru_nvcsw": 9
        },
        "totalObjSize": 146752,
        "cpu_cycles_end": 592652266268733,
        "outputSizePerQuad": 17.224413145539906,
        "cpu_cycles_total": 22748721750,
        "mopSpeed": 262795.53886052541,
        "quadSpeed": 99084.745368485921,
        "mop/quad": 2.6522300469483566,
        "peak_mem_kb": 196432,
        "realTime": 6.9240139711182564
    },
    "CurCompileUdps": {},
    "SIMBData": {
        "out": "amcQwB.o",
        "bytes": 66336,
        "text": 0,
        "archive": "archive.52/_6051_archive_1.a"
    },
    "incremental": "on",
    "Misc": {
        "cwd": "/home/DICS_LAB/M10912039/CIC/CIC_2009_grad/sim",
        "vcs_version": "O-2018.09",
        "hostname": "dics03.ee.yuntech.edu.tw",
        "vcs_build_date": "Build Date = Aug 30 2018 20:25:16",
        "master_pid": 6051,
        "VCS_HOME": "/usr/cad/synopsys/vcs/cur/",
        "csrc": "csrc",
        "csrc_abs": "/home/DICS_LAB/M10912039/CIC/CIC_2009_grad/sim/csrc",
        "daidir": "simv.daidir",
        "daidir_abs": "/home/DICS_LAB/M10912039/CIC/CIC_2009_grad/sim/simv.daidir",
        "default_output_dir": "csrc",
        "archive_dir": "archive.52"
    },
    "rlimit": {
        "data": -1,
        "stack": 134217728
    }
}